reginald/__init__.py
reginald/__main__.py
reginald/bits.py
reginald/cli.py
reginald/datamodel.py
reginald/error.py
reginald/generator.py
reginald/jinja2_generator.py
reginald/utils.py
reginald/builtin_generators/external_jinja2_template.py
reginald/builtin_generators/c/funcpack.py
reginald/builtin_generators/c/macromap.py
reginald/builtin_generators/md/doc.py
reginald/builtin_generators/md/regdumpanalysis.py
reginald/builtin_templates/c/macromap.h
reginald/input/convert_yaml.py
reginald/input/parse_yaml.py
reginald/input/validate_map.py
reginald-0.0.3.dist-info/METADATA
reginald-0.0.3.dist-info/WHEEL
reginald-0.0.3.dist-info/licenses/LICENSE
reginald-0.0.3.dist-info/RECORD
